<?xml version="1.0" encoding="UTF-8"?>
<MetaDataObject xmlns="http://v8.1c.ru/8.3/MDClasses" xmlns:app="http://v8.1c.ru/8.2/managed-application/core" xmlns:cfg="http://v8.1c.ru/8.1/data/enterprise/current-config" xmlns:cmi="http://v8.1c.ru/8.2/managed-application/cmi" xmlns:ent="http://v8.1c.ru/8.1/data/enterprise" xmlns:lf="http://v8.1c.ru/8.2/managed-application/logform" xmlns:style="http://v8.1c.ru/8.1/data/ui/style" xmlns:sys="http://v8.1c.ru/8.1/data/ui/fonts/system" xmlns:v8="http://v8.1c.ru/8.1/data/core" xmlns:v8ui="http://v8.1c.ru/8.1/data/ui" xmlns:web="http://v8.1c.ru/8.1/data/ui/colors/web" xmlns:win="http://v8.1c.ru/8.1/data/ui/colors/windows" xmlns:xen="http://v8.1c.ru/8.3/xcf/enums" xmlns:xpr="http://v8.1c.ru/8.3/xcf/predef" xmlns:xr="http://v8.1c.ru/8.3/xcf/readable" xmlns:xs="http://www.w3.org/2001/XMLSchema" xmlns:xsi="http://www.w3.org/2001/XMLSchema-instance" version="2.20">
	<CalculationRegister uuid="70e65c31-55b3-40e5-9f88-ae29971ef2e7">
		<InternalInfo>
			<xr:GeneratedType name="CalculationRegisterRecord.уатУдержания" category="Record">
				<xr:TypeId>dbaaa053-5163-4688-94f9-b9a011b90dd6</xr:TypeId>
				<xr:ValueId>dd109b22-08ed-427f-8a28-335f7cdc6325</xr:ValueId>
			</xr:GeneratedType>
			<xr:GeneratedType name="CalculationRegisterManager.уатУдержания" category="Manager">
				<xr:TypeId>6e6c93b7-e7e0-42f9-9f8b-0af65e9bc212</xr:TypeId>
				<xr:ValueId>310b5e85-3140-43d7-b1a6-c518ed48db76</xr:ValueId>
			</xr:GeneratedType>
			<xr:GeneratedType name="CalculationRegisterSelection.уатУдержания" category="Selection">
				<xr:TypeId>5f9a83c8-b03b-4ced-b590-e06bae738b7b</xr:TypeId>
				<xr:ValueId>84c10327-edf3-411a-bf67-60982bf9d6b8</xr:ValueId>
			</xr:GeneratedType>
			<xr:GeneratedType name="CalculationRegisterList.уатУдержания" category="List">
				<xr:TypeId>67628784-d1e7-4a32-bb83-98d8702bcb1a</xr:TypeId>
				<xr:ValueId>4a3a510d-feca-4cd3-baf1-6b9529918edb</xr:ValueId>
			</xr:GeneratedType>
			<xr:GeneratedType name="CalculationRegisterRecordSet.уатУдержания" category="RecordSet">
				<xr:TypeId>6fc3d7ce-b86b-45b3-8a7d-807d666c5621</xr:TypeId>
				<xr:ValueId>a9bfcd8a-3b67-4218-985f-c12a25f776e9</xr:ValueId>
			</xr:GeneratedType>
			<xr:GeneratedType name="CalculationRegisterRecordKey.уатУдержания" category="RecordKey">
				<xr:TypeId>a2770091-2170-4853-b930-5c472e56f2bf</xr:TypeId>
				<xr:ValueId>937c0659-52b6-480e-98e3-60c0ec9434ef</xr:ValueId>
			</xr:GeneratedType>
			<xr:GeneratedType name="RecalculationsManager.уатУдержания" category="Recalcs">
				<xr:TypeId>c262797c-1590-4299-bfa3-9754e79663a5</xr:TypeId>
				<xr:ValueId>8d29e696-c5a4-4c11-8ca6-fde2de9d10d6</xr:ValueId>
			</xr:GeneratedType>
		</InternalInfo>
		<Properties>
			<Name>уатУдержания</Name>
			<Synonym>
				<v8:item>
					<v8:lang>en</v8:lang>
					<v8:content>Retentions</v8:content>
				</v8:item>
				<v8:item>
					<v8:lang>ru</v8:lang>
					<v8:content>Удержания</v8:content>
				</v8:item>
			</Synonym>
			<Comment/>
			<UseStandardCommands>true</UseStandardCommands>
			<DefaultListForm>CalculationRegister.уатУдержания.Form.ФормаСписка</DefaultListForm>
			<AuxiliaryListForm/>
			<Periodicity>Month</Periodicity>
			<ActionPeriod>false</ActionPeriod>
			<BasePeriod>true</BasePeriod>
			<Schedule/>
			<ScheduleValue/>
			<ScheduleDate/>
			<ChartOfCalculationTypes>ChartOfCalculationTypes.уатУдержания</ChartOfCalculationTypes>
			<IncludeHelpInContents>true</IncludeHelpInContents>
			<StandardAttributes>
				<xr:StandardAttribute name="RegistrationPeriod">
					<xr:LinkByType/>
					<xr:FillChecking>ShowError</xr:FillChecking>
					<xr:MultiLine>false</xr:MultiLine>
					<xr:FillFromFillingValue>false</xr:FillFromFillingValue>
					<xr:CreateOnInput>Auto</xr:CreateOnInput>
					<xr:TypeReductionMode>TransformValues</xr:TypeReductionMode>
					<xr:MaxValue xsi:nil="true"/>
					<xr:ToolTip/>
					<xr:ExtendedEdit>false</xr:ExtendedEdit>
					<xr:Format/>
					<xr:ChoiceForm/>
					<xr:QuickChoice>Auto</xr:QuickChoice>
					<xr:ChoiceHistoryOnInput>Auto</xr:ChoiceHistoryOnInput>
					<xr:EditFormat/>
					<xr:PasswordMode>false</xr:PasswordMode>
					<xr:DataHistory>Use</xr:DataHistory>
					<xr:MarkNegatives>false</xr:MarkNegatives>
					<xr:MinValue xsi:nil="true"/>
					<xr:Synonym/>
					<xr:Comment/>
					<xr:FullTextSearch>Use</xr:FullTextSearch>
					<xr:ChoiceParameterLinks/>
					<xr:FillValue xsi:nil="true"/>
					<xr:Mask/>
					<xr:ChoiceParameters/>
				</xr:StandardAttribute>
				<xr:StandardAttribute name="ReversingEntry">
					<xr:LinkByType/>
					<xr:FillChecking>DontCheck</xr:FillChecking>
					<xr:MultiLine>false</xr:MultiLine>
					<xr:FillFromFillingValue>false</xr:FillFromFillingValue>
					<xr:CreateOnInput>Auto</xr:CreateOnInput>
					<xr:TypeReductionMode>TransformValues</xr:TypeReductionMode>
					<xr:MaxValue xsi:nil="true"/>
					<xr:ToolTip/>
					<xr:ExtendedEdit>false</xr:ExtendedEdit>
					<xr:Format/>
					<xr:ChoiceForm/>
					<xr:QuickChoice>Auto</xr:QuickChoice>
					<xr:ChoiceHistoryOnInput>Auto</xr:ChoiceHistoryOnInput>
					<xr:EditFormat/>
					<xr:PasswordMode>false</xr:PasswordMode>
					<xr:DataHistory>Use</xr:DataHistory>
					<xr:MarkNegatives>false</xr:MarkNegatives>
					<xr:MinValue xsi:nil="true"/>
					<xr:Synonym/>
					<xr:Comment/>
					<xr:FullTextSearch>Use</xr:FullTextSearch>
					<xr:ChoiceParameterLinks/>
					<xr:FillValue xsi:nil="true"/>
					<xr:Mask/>
					<xr:ChoiceParameters/>
				</xr:StandardAttribute>
				<xr:StandardAttribute name="Active">
					<xr:LinkByType/>
					<xr:FillChecking>DontCheck</xr:FillChecking>
					<xr:MultiLine>false</xr:MultiLine>
					<xr:FillFromFillingValue>false</xr:FillFromFillingValue>
					<xr:CreateOnInput>Auto</xr:CreateOnInput>
					<xr:TypeReductionMode>TransformValues</xr:TypeReductionMode>
					<xr:MaxValue xsi:nil="true"/>
					<xr:ToolTip/>
					<xr:ExtendedEdit>false</xr:ExtendedEdit>
					<xr:Format/>
					<xr:ChoiceForm/>
					<xr:QuickChoice>Auto</xr:QuickChoice>
					<xr:ChoiceHistoryOnInput>Auto</xr:ChoiceHistoryOnInput>
					<xr:EditFormat/>
					<xr:PasswordMode>false</xr:PasswordMode>
					<xr:DataHistory>Use</xr:DataHistory>
					<xr:MarkNegatives>false</xr:MarkNegatives>
					<xr:MinValue xsi:nil="true"/>
					<xr:Synonym/>
					<xr:Comment/>
					<xr:FullTextSearch>Use</xr:FullTextSearch>
					<xr:ChoiceParameterLinks/>
					<xr:FillValue xsi:nil="true"/>
					<xr:Mask/>
					<xr:ChoiceParameters/>
				</xr:StandardAttribute>
				<xr:StandardAttribute name="EndOfBasePeriod">
					<xr:LinkByType/>
					<xr:FillChecking>DontCheck</xr:FillChecking>
					<xr:MultiLine>false</xr:MultiLine>
					<xr:FillFromFillingValue>false</xr:FillFromFillingValue>
					<xr:CreateOnInput>Auto</xr:CreateOnInput>
					<xr:TypeReductionMode>TransformValues</xr:TypeReductionMode>
					<xr:MaxValue xsi:nil="true"/>
					<xr:ToolTip/>
					<xr:ExtendedEdit>false</xr:ExtendedEdit>
					<xr:Format/>
					<xr:ChoiceForm/>
					<xr:QuickChoice>Auto</xr:QuickChoice>
					<xr:ChoiceHistoryOnInput>Auto</xr:ChoiceHistoryOnInput>
					<xr:EditFormat/>
					<xr:PasswordMode>false</xr:PasswordMode>
					<xr:DataHistory>Use</xr:DataHistory>
					<xr:MarkNegatives>false</xr:MarkNegatives>
					<xr:MinValue xsi:nil="true"/>
					<xr:Synonym/>
					<xr:Comment/>
					<xr:FullTextSearch>Use</xr:FullTextSearch>
					<xr:ChoiceParameterLinks/>
					<xr:FillValue xsi:nil="true"/>
					<xr:Mask/>
					<xr:ChoiceParameters/>
				</xr:StandardAttribute>
				<xr:StandardAttribute name="BegOfBasePeriod">
					<xr:LinkByType/>
					<xr:FillChecking>DontCheck</xr:FillChecking>
					<xr:MultiLine>false</xr:MultiLine>
					<xr:FillFromFillingValue>false</xr:FillFromFillingValue>
					<xr:CreateOnInput>Auto</xr:CreateOnInput>
					<xr:TypeReductionMode>TransformValues</xr:TypeReductionMode>
					<xr:MaxValue xsi:nil="true"/>
					<xr:ToolTip/>
					<xr:ExtendedEdit>false</xr:ExtendedEdit>
					<xr:Format/>
					<xr:ChoiceForm/>
					<xr:QuickChoice>Auto</xr:QuickChoice>
					<xr:ChoiceHistoryOnInput>Auto</xr:ChoiceHistoryOnInput>
					<xr:EditFormat/>
					<xr:PasswordMode>false</xr:PasswordMode>
					<xr:DataHistory>Use</xr:DataHistory>
					<xr:MarkNegatives>false</xr:MarkNegatives>
					<xr:MinValue xsi:nil="true"/>
					<xr:Synonym/>
					<xr:Comment/>
					<xr:FullTextSearch>Use</xr:FullTextSearch>
					<xr:ChoiceParameterLinks/>
					<xr:FillValue xsi:nil="true"/>
					<xr:Mask/>
					<xr:ChoiceParameters/>
				</xr:StandardAttribute>
				<xr:StandardAttribute name="EndOfActionPeriod">
					<xr:LinkByType/>
					<xr:FillChecking>ShowError</xr:FillChecking>
					<xr:MultiLine>false</xr:MultiLine>
					<xr:FillFromFillingValue>false</xr:FillFromFillingValue>
					<xr:CreateOnInput>Auto</xr:CreateOnInput>
					<xr:TypeReductionMode>TransformValues</xr:TypeReductionMode>
					<xr:MaxValue xsi:nil="true"/>
					<xr:ToolTip/>
					<xr:ExtendedEdit>false</xr:ExtendedEdit>
					<xr:Format/>
					<xr:ChoiceForm/>
					<xr:QuickChoice>Auto</xr:QuickChoice>
					<xr:ChoiceHistoryOnInput>Auto</xr:ChoiceHistoryOnInput>
					<xr:EditFormat/>
					<xr:PasswordMode>false</xr:PasswordMode>
					<xr:DataHistory>Use</xr:DataHistory>
					<xr:MarkNegatives>false</xr:MarkNegatives>
					<xr:MinValue xsi:nil="true"/>
					<xr:Synonym/>
					<xr:Comment/>
					<xr:FullTextSearch>Use</xr:FullTextSearch>
					<xr:ChoiceParameterLinks/>
					<xr:FillValue xsi:nil="true"/>
					<xr:Mask/>
					<xr:ChoiceParameters/>
				</xr:StandardAttribute>
				<xr:StandardAttribute name="BegOfActionPeriod">
					<xr:LinkByType/>
					<xr:FillChecking>ShowError</xr:FillChecking>
					<xr:MultiLine>false</xr:MultiLine>
					<xr:FillFromFillingValue>false</xr:FillFromFillingValue>
					<xr:CreateOnInput>Auto</xr:CreateOnInput>
					<xr:TypeReductionMode>TransformValues</xr:TypeReductionMode>
					<xr:MaxValue xsi:nil="true"/>
					<xr:ToolTip/>
					<xr:ExtendedEdit>false</xr:ExtendedEdit>
					<xr:Format/>
					<xr:ChoiceForm/>
					<xr:QuickChoice>Auto</xr:QuickChoice>
					<xr:ChoiceHistoryOnInput>Auto</xr:ChoiceHistoryOnInput>
					<xr:EditFormat/>
					<xr:PasswordMode>false</xr:PasswordMode>
					<xr:DataHistory>Use</xr:DataHistory>
					<xr:MarkNegatives>false</xr:MarkNegatives>
					<xr:MinValue xsi:nil="true"/>
					<xr:Synonym/>
					<xr:Comment/>
					<xr:FullTextSearch>Use</xr:FullTextSearch>
					<xr:ChoiceParameterLinks/>
					<xr:FillValue xsi:nil="true"/>
					<xr:Mask/>
					<xr:ChoiceParameters/>
				</xr:StandardAttribute>
				<xr:StandardAttribute name="ActionPeriod">
					<xr:LinkByType/>
					<xr:FillChecking>DontCheck</xr:FillChecking>
					<xr:MultiLine>false</xr:MultiLine>
					<xr:FillFromFillingValue>false</xr:FillFromFillingValue>
					<xr:CreateOnInput>Auto</xr:CreateOnInput>
					<xr:TypeReductionMode>TransformValues</xr:TypeReductionMode>
					<xr:MaxValue xsi:nil="true"/>
					<xr:ToolTip/>
					<xr:ExtendedEdit>false</xr:ExtendedEdit>
					<xr:Format/>
					<xr:ChoiceForm/>
					<xr:QuickChoice>Auto</xr:QuickChoice>
					<xr:ChoiceHistoryOnInput>Auto</xr:ChoiceHistoryOnInput>
					<xr:EditFormat/>
					<xr:PasswordMode>false</xr:PasswordMode>
					<xr:DataHistory>Use</xr:DataHistory>
					<xr:MarkNegatives>false</xr:MarkNegatives>
					<xr:MinValue xsi:nil="true"/>
					<xr:Synonym/>
					<xr:Comment/>
					<xr:FullTextSearch>Use</xr:FullTextSearch>
					<xr:ChoiceParameterLinks/>
					<xr:FillValue xsi:nil="true"/>
					<xr:Mask/>
					<xr:ChoiceParameters/>
				</xr:StandardAttribute>
				<xr:StandardAttribute name="CalculationType">
					<xr:LinkByType/>
					<xr:FillChecking>ShowError</xr:FillChecking>
					<xr:MultiLine>false</xr:MultiLine>
					<xr:FillFromFillingValue>false</xr:FillFromFillingValue>
					<xr:CreateOnInput>Auto</xr:CreateOnInput>
					<xr:TypeReductionMode>TransformValues</xr:TypeReductionMode>
					<xr:MaxValue xsi:nil="true"/>
					<xr:ToolTip/>
					<xr:ExtendedEdit>false</xr:ExtendedEdit>
					<xr:Format/>
					<xr:ChoiceForm/>
					<xr:QuickChoice>Auto</xr:QuickChoice>
					<xr:ChoiceHistoryOnInput>Auto</xr:ChoiceHistoryOnInput>
					<xr:EditFormat/>
					<xr:PasswordMode>false</xr:PasswordMode>
					<xr:DataHistory>Use</xr:DataHistory>
					<xr:MarkNegatives>false</xr:MarkNegatives>
					<xr:MinValue xsi:nil="true"/>
					<xr:Synonym/>
					<xr:Comment/>
					<xr:FullTextSearch>Use</xr:FullTextSearch>
					<xr:ChoiceParameterLinks/>
					<xr:FillValue xsi:nil="true"/>
					<xr:Mask/>
					<xr:ChoiceParameters/>
				</xr:StandardAttribute>
				<xr:StandardAttribute name="LineNumber">
					<xr:LinkByType/>
					<xr:FillChecking>DontCheck</xr:FillChecking>
					<xr:MultiLine>false</xr:MultiLine>
					<xr:FillFromFillingValue>false</xr:FillFromFillingValue>
					<xr:CreateOnInput>Auto</xr:CreateOnInput>
					<xr:TypeReductionMode>TransformValues</xr:TypeReductionMode>
					<xr:MaxValue xsi:nil="true"/>
					<xr:ToolTip/>
					<xr:ExtendedEdit>false</xr:ExtendedEdit>
					<xr:Format/>
					<xr:ChoiceForm/>
					<xr:QuickChoice>Auto</xr:QuickChoice>
					<xr:ChoiceHistoryOnInput>Auto</xr:ChoiceHistoryOnInput>
					<xr:EditFormat/>
					<xr:PasswordMode>false</xr:PasswordMode>
					<xr:DataHistory>Use</xr:DataHistory>
					<xr:MarkNegatives>false</xr:MarkNegatives>
					<xr:MinValue xsi:nil="true"/>
					<xr:Synonym/>
					<xr:Comment/>
					<xr:FullTextSearch>Use</xr:FullTextSearch>
					<xr:ChoiceParameterLinks/>
					<xr:FillValue xsi:nil="true"/>
					<xr:Mask/>
					<xr:ChoiceParameters/>
				</xr:StandardAttribute>
				<xr:StandardAttribute name="Recorder">
					<xr:LinkByType/>
					<xr:FillChecking>DontCheck</xr:FillChecking>
					<xr:MultiLine>false</xr:MultiLine>
					<xr:FillFromFillingValue>false</xr:FillFromFillingValue>
					<xr:CreateOnInput>Auto</xr:CreateOnInput>
					<xr:TypeReductionMode>TransformValues</xr:TypeReductionMode>
					<xr:MaxValue xsi:nil="true"/>
					<xr:ToolTip/>
					<xr:ExtendedEdit>false</xr:ExtendedEdit>
					<xr:Format/>
					<xr:ChoiceForm/>
					<xr:QuickChoice>Auto</xr:QuickChoice>
					<xr:ChoiceHistoryOnInput>Auto</xr:ChoiceHistoryOnInput>
					<xr:EditFormat/>
					<xr:PasswordMode>false</xr:PasswordMode>
					<xr:DataHistory>Use</xr:DataHistory>
					<xr:MarkNegatives>false</xr:MarkNegatives>
					<xr:MinValue xsi:nil="true"/>
					<xr:Synonym/>
					<xr:Comment/>
					<xr:FullTextSearch>Use</xr:FullTextSearch>
					<xr:ChoiceParameterLinks/>
					<xr:FillValue xsi:nil="true"/>
					<xr:Mask/>
					<xr:ChoiceParameters/>
				</xr:StandardAttribute>
			</StandardAttributes>
			<DataLockControlMode>Managed</DataLockControlMode>
			<FullTextSearch>DontUse</FullTextSearch>
			<ListPresentation>
				<v8:item>
					<v8:lang>ru</v8:lang>
					<v8:content>Удержания</v8:content>
				</v8:item>
				<v8:item>
					<v8:lang>en</v8:lang>
					<v8:content>Deductions</v8:content>
				</v8:item>
			</ListPresentation>
			<ExtendedListPresentation>
				<v8:item>
					<v8:lang>ru</v8:lang>
					<v8:content>Удержания</v8:content>
				</v8:item>
				<v8:item>
					<v8:lang>en</v8:lang>
					<v8:content>Deductions</v8:content>
				</v8:item>
			</ExtendedListPresentation>
			<Explanation/>
		</Properties>
		<ChildObjects>
			<Resource uuid="949fc2e3-d8dd-45c1-8be3-d28a76e8422a">
				<Properties>
					<Name>Результат</Name>
					<Synonym>
						<v8:item>
							<v8:lang>ru</v8:lang>
							<v8:content>Результат</v8:content>
						</v8:item>
						<v8:item>
							<v8:lang>en</v8:lang>
							<v8:content>Result</v8:content>
						</v8:item>
					</Synonym>
					<Comment/>
					<Type>
						<v8:Type>xs:decimal</v8:Type>
						<v8:NumberQualifiers>
							<v8:Digits>15</v8:Digits>
							<v8:FractionDigits>2</v8:FractionDigits>
							<v8:AllowedSign>Any</v8:AllowedSign>
						</v8:NumberQualifiers>
					</Type>
					<PasswordMode>false</PasswordMode>
					<Format/>
					<EditFormat/>
					<ToolTip>
						<v8:item>
							<v8:lang>en</v8:lang>
							<v8:content>Result of calculation in currency of management accounting</v8:content>
						</v8:item>
						<v8:item>
							<v8:lang>ru</v8:lang>
							<v8:content>Результат удержания в валюте управленческого учета</v8:content>
						</v8:item>
					</ToolTip>
					<MarkNegatives>false</MarkNegatives>
					<Mask/>
					<MultiLine>false</MultiLine>
					<ExtendedEdit>false</ExtendedEdit>
					<MinValue xsi:nil="true"/>
					<MaxValue xsi:nil="true"/>
					<FillChecking>DontCheck</FillChecking>
					<ChoiceFoldersAndItems>Items</ChoiceFoldersAndItems>
					<ChoiceParameterLinks/>
					<ChoiceParameters/>
					<QuickChoice>Auto</QuickChoice>
					<CreateOnInput>Auto</CreateOnInput>
					<ChoiceForm/>
					<LinkByType/>
					<ChoiceHistoryOnInput>Auto</ChoiceHistoryOnInput>
					<FullTextSearch>Use</FullTextSearch>
				</Properties>
			</Resource>
			<Dimension uuid="8ae7f2a9-62c4-441f-ac49-6014173113b6">
				<Properties>
					<Name>Организация</Name>
					<Synonym>
						<v8:item>
							<v8:lang>ru</v8:lang>
							<v8:content>Организация</v8:content>
						</v8:item>
						<v8:item>
							<v8:lang>en</v8:lang>
							<v8:content>Company</v8:content>
						</v8:item>
					</Synonym>
					<Comment>Организация</Comment>
					<Type>
						<v8:Type>cfg:CatalogRef.Организации</v8:Type>
					</Type>
					<PasswordMode>false</PasswordMode>
					<Format/>
					<EditFormat/>
					<ToolTip>
						<v8:item>
							<v8:lang>ru</v8:lang>
							<v8:content>Организация, по которой ведется расчет начислений заработной платы</v8:content>
						</v8:item>
						<v8:item>
							<v8:lang>en</v8:lang>
							<v8:content>Company, for accounting of salary accrual</v8:content>
						</v8:item>
					</ToolTip>
					<MarkNegatives>false</MarkNegatives>
					<Mask/>
					<MultiLine>false</MultiLine>
					<ExtendedEdit>false</ExtendedEdit>
					<MinValue xsi:nil="true"/>
					<MaxValue xsi:nil="true"/>
					<FillChecking>DontCheck</FillChecking>
					<ChoiceFoldersAndItems>Items</ChoiceFoldersAndItems>
					<ChoiceParameterLinks/>
					<ChoiceParameters/>
					<QuickChoice>Auto</QuickChoice>
					<CreateOnInput>Auto</CreateOnInput>
					<ChoiceForm/>
					<LinkByType/>
					<ChoiceHistoryOnInput>Auto</ChoiceHistoryOnInput>
					<DenyIncompleteValues>true</DenyIncompleteValues>
					<BaseDimension>false</BaseDimension>
					<ScheduleLink/>
					<Indexing>Index</Indexing>
					<FullTextSearch>Use</FullTextSearch>
				</Properties>
			</Dimension>
			<Dimension uuid="9e42e8bb-5ff8-474b-bf51-949313181928">
				<Properties>
					<Name>Подразделение</Name>
					<Synonym>
						<v8:item>
							<v8:lang>ru</v8:lang>
							<v8:content>Подразделение</v8:content>
						</v8:item>
						<v8:item>
							<v8:lang>en</v8:lang>
							<v8:content>Subdivision</v8:content>
						</v8:item>
					</Synonym>
					<Comment/>
					<Type>
						<v8:Type>cfg:CatalogRef.ПодразделенияОрганизаций</v8:Type>
					</Type>
					<PasswordMode>false</PasswordMode>
					<Format/>
					<EditFormat/>
					<ToolTip/>
					<MarkNegatives>false</MarkNegatives>
					<Mask/>
					<MultiLine>false</MultiLine>
					<ExtendedEdit>false</ExtendedEdit>
					<MinValue xsi:nil="true"/>
					<MaxValue xsi:nil="true"/>
					<FillChecking>DontCheck</FillChecking>
					<ChoiceFoldersAndItems>Items</ChoiceFoldersAndItems>
					<ChoiceParameterLinks/>
					<ChoiceParameters/>
					<QuickChoice>Auto</QuickChoice>
					<CreateOnInput>Auto</CreateOnInput>
					<ChoiceForm/>
					<LinkByType/>
					<ChoiceHistoryOnInput>Auto</ChoiceHistoryOnInput>
					<DenyIncompleteValues>false</DenyIncompleteValues>
					<BaseDimension>false</BaseDimension>
					<ScheduleLink/>
					<Indexing>DontIndex</Indexing>
					<FullTextSearch>Use</FullTextSearch>
				</Properties>
			</Dimension>
			<Dimension uuid="ba2ad4d3-19e6-4a80-a824-0fe4343c55d0">
				<Properties>
					<Name>Сотрудник</Name>
					<Synonym>
						<v8:item>
							<v8:lang>ru</v8:lang>
							<v8:content>Сотрудник</v8:content>
						</v8:item>
						<v8:item>
							<v8:lang>en</v8:lang>
							<v8:content>Employee</v8:content>
						</v8:item>
					</Synonym>
					<Comment>Сотрудник</Comment>
					<Type>
						<v8:Type>cfg:CatalogRef.Сотрудники</v8:Type>
					</Type>
					<PasswordMode>false</PasswordMode>
					<Format/>
					<EditFormat/>
					<ToolTip>
						<v8:item>
							<v8:lang>ru</v8:lang>
							<v8:content>Сотрудник, по которому ведется расчет начислений заработной платы</v8:content>
						</v8:item>
						<v8:item>
							<v8:lang>en</v8:lang>
							<v8:content>Employee, under which the calculation of salary</v8:content>
						</v8:item>
					</ToolTip>
					<MarkNegatives>false</MarkNegatives>
					<Mask/>
					<MultiLine>false</MultiLine>
					<ExtendedEdit>false</ExtendedEdit>
					<MinValue xsi:nil="true"/>
					<MaxValue xsi:nil="true"/>
					<FillChecking>DontCheck</FillChecking>
					<ChoiceFoldersAndItems>Items</ChoiceFoldersAndItems>
					<ChoiceParameterLinks/>
					<ChoiceParameters/>
					<QuickChoice>Auto</QuickChoice>
					<CreateOnInput>Auto</CreateOnInput>
					<ChoiceForm/>
					<LinkByType/>
					<ChoiceHistoryOnInput>Auto</ChoiceHistoryOnInput>
					<DenyIncompleteValues>true</DenyIncompleteValues>
					<BaseDimension>true</BaseDimension>
					<ScheduleLink/>
					<Indexing>DontIndex</Indexing>
					<FullTextSearch>Use</FullTextSearch>
				</Properties>
			</Dimension>
			<Dimension uuid="bdcb8b95-9475-41c2-bd3f-753366bf42a2">
				<Properties>
					<Name>Тариф</Name>
					<Synonym>
						<v8:item>
							<v8:lang>ru</v8:lang>
							<v8:content>Тариф</v8:content>
						</v8:item>
						<v8:item>
							<v8:lang>en</v8:lang>
							<v8:content>Tariff</v8:content>
						</v8:item>
					</Synonym>
					<Comment/>
					<Type>
						<v8:Type>cfg:CatalogRef.уатТарифыЗП</v8:Type>
					</Type>
					<PasswordMode>false</PasswordMode>
					<Format/>
					<EditFormat/>
					<ToolTip/>
					<MarkNegatives>false</MarkNegatives>
					<Mask/>
					<MultiLine>false</MultiLine>
					<ExtendedEdit>false</ExtendedEdit>
					<MinValue xsi:nil="true"/>
					<MaxValue xsi:nil="true"/>
					<FillChecking>DontCheck</FillChecking>
					<ChoiceFoldersAndItems>Items</ChoiceFoldersAndItems>
					<ChoiceParameterLinks/>
					<ChoiceParameters/>
					<QuickChoice>Auto</QuickChoice>
					<CreateOnInput>Auto</CreateOnInput>
					<ChoiceForm/>
					<LinkByType/>
					<ChoiceHistoryOnInput>Auto</ChoiceHistoryOnInput>
					<DenyIncompleteValues>false</DenyIncompleteValues>
					<BaseDimension>false</BaseDimension>
					<ScheduleLink/>
					<Indexing>DontIndex</Indexing>
					<FullTextSearch>Use</FullTextSearch>
				</Properties>
			</Dimension>
			<Dimension uuid="0fa37775-bec4-4c99-9aea-55735824f74d">
				<Properties>
					<Name>ТС</Name>
					<Synonym>
						<v8:item>
							<v8:lang>ru</v8:lang>
							<v8:content>ТС</v8:content>
						</v8:item>
						<v8:item>
							<v8:lang>en</v8:lang>
							<v8:content>Vehicle</v8:content>
						</v8:item>
					</Synonym>
					<Comment/>
					<Type>
						<v8:Type>cfg:CatalogRef.уатТС</v8:Type>
					</Type>
					<PasswordMode>false</PasswordMode>
					<Format/>
					<EditFormat/>
					<ToolTip/>
					<MarkNegatives>false</MarkNegatives>
					<Mask/>
					<MultiLine>false</MultiLine>
					<ExtendedEdit>false</ExtendedEdit>
					<MinValue xsi:nil="true"/>
					<MaxValue xsi:nil="true"/>
					<FillChecking>DontCheck</FillChecking>
					<ChoiceFoldersAndItems>Items</ChoiceFoldersAndItems>
					<ChoiceParameterLinks/>
					<ChoiceParameters/>
					<QuickChoice>Auto</QuickChoice>
					<CreateOnInput>Auto</CreateOnInput>
					<ChoiceForm/>
					<LinkByType/>
					<ChoiceHistoryOnInput>Auto</ChoiceHistoryOnInput>
					<DenyIncompleteValues>false</DenyIncompleteValues>
					<BaseDimension>false</BaseDimension>
					<ScheduleLink/>
					<Indexing>DontIndex</Indexing>
					<FullTextSearch>Use</FullTextSearch>
				</Properties>
			</Dimension>
			<Form>ФормаСписка</Form>
		</ChildObjects>
	</CalculationRegister>
</MetaDataObject>