<?xml version="1.0" encoding="UTF-8"?>
<MetaDataObject xmlns="http://v8.1c.ru/8.3/MDClasses" xmlns:app="http://v8.1c.ru/8.2/managed-application/core" xmlns:cfg="http://v8.1c.ru/8.1/data/enterprise/current-config" xmlns:cmi="http://v8.1c.ru/8.2/managed-application/cmi" xmlns:ent="http://v8.1c.ru/8.1/data/enterprise" xmlns:lf="http://v8.1c.ru/8.2/managed-application/logform" xmlns:style="http://v8.1c.ru/8.1/data/ui/style" xmlns:sys="http://v8.1c.ru/8.1/data/ui/fonts/system" xmlns:v8="http://v8.1c.ru/8.1/data/core" xmlns:v8ui="http://v8.1c.ru/8.1/data/ui" xmlns:web="http://v8.1c.ru/8.1/data/ui/colors/web" xmlns:win="http://v8.1c.ru/8.1/data/ui/colors/windows" xmlns:xen="http://v8.1c.ru/8.3/xcf/enums" xmlns:xpr="http://v8.1c.ru/8.3/xcf/predef" xmlns:xr="http://v8.1c.ru/8.3/xcf/readable" xmlns:xs="http://www.w3.org/2001/XMLSchema" xmlns:xsi="http://www.w3.org/2001/XMLSchema-instance" version="2.20">
	<FunctionalOption uuid="067f02a4-71cb-4210-ab16-5999b2fed669">
		<Properties>
			<Name>уатИспользоватьАвтоматическуюМаршрутизацию</Name>
			<Synonym>
				<v8:item>
					<v8:lang>en</v8:lang>
					<v8:content>Use automatic routing</v8:content>
				</v8:item>
				<v8:item>
					<v8:lang>ru</v8:lang>
					<v8:content>Использовать автоматическую маршрутизацию</v8:content>
				</v8:item>
			</Synonym>
			<Comment>(уат)</Comment>
			<Location>Constant.уатИспользоватьАвтоматическуюМаршрутизацию_уэ</Location>
			<PrivilegedGetMode>true</PrivilegedGetMode>
			<Content>
				<xr:Object>Catalog.уатТС.Attribute.ШтрафЗаНевыполнениеЗаказа</xr:Object>
				<xr:Object>Catalog.уатТС.Attribute.ШтрафЗаНевыполнениеЗаказаФиксир</xr:Object>
				<xr:Object>Catalog.уатТС.Attribute.ШтрафЗаОкноМинута</xr:Object>
				<xr:Object>Catalog.уатТС.Attribute.ШтрафЗаОкноМинутаПозднее</xr:Object>
				<xr:Object>Catalog.уатТС.Attribute.ШтрафЗаОкноМинутаРанее</xr:Object>
				<xr:Object>Catalog.уатТС.Attribute.ШтрафЗаОкноФиксир</xr:Object>
				<xr:Object>Catalog.уатТС.Attribute.ШтрафЗаОкноФиксирПозднее</xr:Object>
				<xr:Object>Catalog.уатТС.Attribute.ШтрафЗаОкноФиксирРанее</xr:Object>
				<xr:Object>Catalog.уатТС.Attribute.ШтрафЗаПревышениеМаксимумаЗаказов</xr:Object>
				<xr:Object>Catalog.уатТС.Attribute.ШтрафЗаПревышениеМаксимумаЗаказовФиксир</xr:Object>
				<xr:Object>Catalog.уатТС.Attribute.МинимальноеЧислоПунктов</xr:Object>
				<xr:Object>Catalog.уатТС.Attribute.МетодПередвижения</xr:Object>
				<xr:Object>Catalog.уатТС.Attribute.МаксимальноеЧислоПунктов</xr:Object>
				<xr:Object>Catalog.уатТС.Attribute.КоличествоЕздок</xr:Object>
				<xr:Object>Catalog.уатТС.Attribute.ВремяПересменки</xr:Object>
				<xr:Object>Catalog.уатТС.Attribute.СтоимостьТСЗаЕздку</xr:Object>
				<xr:Object>Catalog.уатТС.Attribute.СтоимостьТСЗаЗаказ</xr:Object>
				<xr:Object>Catalog.уатТС.Attribute.СтоимостьТСЗаКм</xr:Object>
				<xr:Object>Catalog.уатТС.Attribute.СтоимостьТСЗаЧас</xr:Object>
				<xr:Object>Catalog.уатТС.Attribute.СтоимостьТСФиксир</xr:Object>
				<xr:Object>Catalog.уатТС.Attribute.КоэффициентКорректирующийВремяНаАдрес</xr:Object>
				<xr:Object>Catalog.уатТС.Attribute.КоэффициентКорректирующийВремяНаОбработкуЗаказа</xr:Object>
				<xr:Object>Catalog.уатМоделиТС.Attribute.СтоимостьТСФиксир</xr:Object>
				<xr:Object>Catalog.уатМоделиТС.Attribute.СтоимостьТСЗаЕздку</xr:Object>
				<xr:Object>Catalog.уатМоделиТС.Attribute.СтоимостьТСЗаКм</xr:Object>
				<xr:Object>Catalog.уатМоделиТС.Attribute.СтоимостьТСЗаЧас</xr:Object>
				<xr:Object>Catalog.уатМоделиТС.Attribute.СтоимостьТСЗаЗаказ</xr:Object>
				<xr:Object>Catalog.уатРежимыРаботыТС.TabularSection.Перерывы</xr:Object>
				<xr:Object>Catalog.уатПунктыНазначения.Attribute.ПропускнаяСпособностьСкладаЕдЧ</xr:Object>
				<xr:Object>Catalog.уатПунктыНазначения.Attribute.ПропускнаяСпособностьСкладаКгЧ</xr:Object>
				<xr:Object>Catalog.уатПунктыНазначения.Attribute.ПропускнаяСпособностьСкладаТС</xr:Object>
				<xr:Object>Catalog.Контрагенты.Attribute.Приоритет</xr:Object>
			</Content>
		</Properties>
	</FunctionalOption>
</MetaDataObject>